{
  "users": [
    {
      "id": "1",
      "email": "joao.silva@email.com",
      "senha": "joao.silva@email.com"
    },
    {
      "id": "2",
      "email": "maria.oliveira@email.com",
      "senha": "senha123"
    },
    {
      "id": "3",
      "email": "carlos.santos@email.com",
      "senha": "senha123"
    }
  ],
  "balances": [
    { "name": "João Silva", "userId": 1, "balance": 5000 },
    { "name": "Maria Oliveira", "userId": 2, "balance": 3500.5 },
    { "name": "Carlos Santos", "userId": 3, "balance": 7800.75 }
  ],
  "transfers": [
    {
      "id": "1",
      "userId": 1,
      "recipient": "Maria Oliveira",
      "amount": 1000,
      "date": "2025-01-10",
      "scheduled": false
    },
    {
      "id": "2",
      "userId": 1,
      "recipient": "Carlos Santos",
      "amount": 500,
      "date": "2025-01-12",
      "scheduled": true
    },
    {
      "id": "3",
      "userId": 2,
      "recipient": "João Silva",
      "amount": 750.5,
      "date": "2025-01-08",
      "scheduled": false
    },
    {
      "id": "4",
      "userId": 3,
      "recipient": "Maria Oliveira",
      "amount": 1500,
      "date": "2025-01-15",
      "scheduled": true
    }
  ]
}
